miqbox/__init__.py
miqbox/client.py
miqbox/config.yaml
miqbox/configuration.py
miqbox/exception.py
miqbox/images.py
miqbox/miq_xmls.py
miqbox/miqbox.py
miqbox/ssh.py
miqbox-1.5.dist-info/LICENSE
miqbox-1.5.dist-info/METADATA
miqbox-1.5.dist-info/WHEEL
miqbox-1.5.dist-info/entry_points.txt
miqbox-1.5.dist-info/top_level.txt
miqbox-1.5.dist-info/RECORD
