Metadata-Version: 2.1
Name: miqbox
Version: 1.5
Summary: Spin ManageIQ/CFME Appliance locally.
Home-page: https://github.com/digitronik/miqbox
Author: Nikhil Dhandre
Author-email: nik.digitronik@live.com
License: UNKNOWN
Keywords: miqbox,ManageIQ,CFME,cloudform
Platform: UNKNOWN
Classifier: Natural Language :: English
Classifier: Programming Language :: Python :: 3.6
Classifier: Programming Language :: Python :: 3.7
Classifier: Programming Language :: Python :: 3.8
Classifier: Intended Audience :: End Users/Desktop
Classifier: Environment :: Console
Classifier: License :: OSI Approved :: GNU General Public License v2 (GPLv2)
Requires-Python: >=3.6
Requires-Dist: bs4
Requires-Dist: Click
Requires-Dist: libvirt-python
Requires-Dist: paramiko
Requires-Dist: requests
Requires-Dist: ruamel.yaml
